{
  "users": [
    {
      "id": 1,
      "email": "v@gmail.com"
    },
    {
      "id": 2,
      "email": "rekha@gmail.com"
    },
    {
      "email": "nk@gmail.com",
      "id": 3
    }
  ],
  "products": [
    {
      "id": 1,
      "title": "First Aid Supplies",
      "src": "https://via.placeholder.com/150",
      "price": 15000,
      "ratings": 3,
      "reviewCount": 32
    },
    {
      "id": 2,
      "title": "Diabetic Medication",
      "src": "https://via.placeholder.com/150",
      "price": 567,
      "ratings": 4,
      "reviewCount": 35
    },
    {
      "id": 3,
      "title": "Liver Medication",
      "src": "https://via.placeholder.com/150",
      "price": 890,
      "ratings": 2,
      "reviewCount": 28
    },
    {
      "id": 4,
      "title": "Heart Medication",
      "src": "https://via.placeholder.com/150",
      "price": 1200,
      "ratings": 5,
      "reviewCount": 42
    },
    {
      "id": 5,
      "title": "Blood Pressure Medication",
      "src": "https://via.placeholder.com/150",
      "price": 750,
      "ratings": 2,
      "reviewCount": 38
    },
    {
      "id": 6,
      "title": "Antibiotic Medication",
      "src": "https://via.placeholder.com/150",
      "price": 620,
      "ratings": 3,
      "reviewCount": 30
    },
    {
      "id": 7,
      "title": "Pain Relief Medication",
      "src": "https://via.placeholder.com/150",
      "price": 350,
      "ratings": 1,
      "reviewCount": 25
    },
    {
      "id": 8,
      "title": "Vitamins and Supplements",
      "src": "https://via.placeholder.com/150",
      "price": 400,
      "ratings": 4,
      "reviewCount": 33
    },
    {
      "id": 9,
      "title": "Allergy Medication",
      "src": "https://via.placeholder.com/150",
      "price": 450,
      "ratings": 2,
      "reviewCount": 37
    },
    {
      "id": 10,
      "title": "Skincare Products",
      "src": "https://via.placeholder.com/150",
      "price": 700,
      "ratings": 5,
      "reviewCount": 40
    },
    {
      "id": 11,
      "title": "Digestive Health Supplements",
      "src": "https://via.placeholder.com/150",
      "price": 380,
      "ratings": 3,
      "reviewCount": 29
    },
    {
      "id": 12,
      "title": "Weight Management Supplements",
      "src": "https://via.placeholder.com/150",
      "price": 550,
      "ratings": 4,
      "reviewCount": 31
    },
    {
      "id": 13,
      "title": "Eye Care Products",
      "src": "https://via.placeholder.com/150",
      "price": 600,
      "ratings": 1,
      "reviewCount": 34
    },
    {
      "id": 14,
      "title": "Oral Health Products",
      "src": "https://via.placeholder.com/150",
      "price": 250,
      "ratings": 0,
      "reviewCount": 23
    },
    {
      "id": 15,
      "title": "Hair Care Products",
      "src": "https://via.placeholder.com/150",
      "price": 800,
      "ratings": 3,
      "reviewCount": 39
    },
    {
      "id": 16,
      "title": "Men's Health Products",
      "src": "https://via.placeholder.com/150",
      "price": 900,
      "ratings": 3,
      "reviewCount": 36
    },
    {
      "id": 17,
      "title": "Women's Health Products",
      "src": "https://via.placeholder.com/150",
      "price": 1000,
      "ratings": 2,
      "reviewCount": 37
    },
    {
      "id": 18,
      "title": "Baby Care Products",
      "src": "https://via.placeholder.com/150",
      "price": 1100,
      "ratings": 5,
      "reviewCount": 41
    },
    {
      "id": 19,
      "title": "First Aid Supplies",
      "src": "https://via.placeholder.com/150",
      "price": 200,
      "ratings": 1,
      "reviewCount": 24
    },
    {
      "id": 20,
      "title": "Pet Care Products",
      "src": "https://via.placeholder.com/150",
      "price": 300,
      "ratings": 3,
      "reviewCount": 26
    }
  ],
  "allUsersCart": {
    "v@gmail.com": [
      {
        "id": 1,
        "title": "First Aid Supplies",
        "src": "https://via.placeholder.com/150",
        "price": 15000,
        "ratings": 3,
        "reviewCount": 32
      },
      {
        "id": 2,
        "title": "Diabetic Medication",
        "src": "https://via.placeholder.com/150",
        "price": 567,
        "ratings": 4,
        "reviewCount": 35
      },
      {
        "id": 3,
        "title": "Liver Medication",
        "src": "https://via.placeholder.com/150",
        "price": 890,
        "ratings": 2,
        "reviewCount": 28
      },
      {
        "id": 10,
        "title": "Skincare Products",
        "src": "https://via.placeholder.com/150",
        "price": 700,
        "ratings": 5,
        "reviewCount": 40
      },
      {
        "id": 7,
        "title": "Pain Relief Medication",
        "src": "https://via.placeholder.com/150",
        "price": 350,
        "ratings": 1,
        "reviewCount": 25
      }
    ],
    "rekha@gmail.com": [
      {
        "id": 1,
        "title": "First Aid Supplies",
        "src": "https://via.placeholder.com/150",
        "price": 15000,
        "ratings": 3,
        "reviewCount": 32
      },
      {
        "id": 2,
        "title": "Diabetic Medication",
        "src": "https://via.placeholder.com/150",
        "price": 567,
        "ratings": 4,
        "reviewCount": 35
      },
      {
        "id": 7,
        "title": "Pain Relief Medication",
        "src": "https://via.placeholder.com/150",
        "price": 350,
        "ratings": 1,
        "reviewCount": 25
      }
    ],
    "nk@gmail.com": [
      {
        "id": 11,
        "title": "Digestive Health Supplements",
        "src": "https://via.placeholder.com/150",
        "price": 380,
        "ratings": 3,
        "reviewCount": 29
      },
      {
        "id": 4,
        "title": "Heart Medication",
        "src": "https://via.placeholder.com/150",
        "price": 1200,
        "ratings": 5,
        "reviewCount": 42
      },
      {
        "id": 3,
        "title": "Liver Medication",
        "src": "https://via.placeholder.com/150",
        "price": 890,
        "ratings": 2,
        "reviewCount": 28
      },
      {
        "id": 1,
        "title": "First Aid Supplies",
        "src": "https://via.placeholder.com/150",
        "price": 15000,
        "ratings": 3,
        "reviewCount": 32
      },
      {
        "id": 2,
        "title": "Diabetic Medication",
        "src": "https://via.placeholder.com/150",
        "price": 567,
        "ratings": 4,
        "reviewCount": 35
      },
      {
        "id": 8,
        "title": "Vitamins and Supplements",
        "src": "https://via.placeholder.com/150",
        "price": 400,
        "ratings": 4,
        "reviewCount": 33
      }
    ]
  }
}